dbt/adapters/fabric/__init__.py
dbt/adapters/fabric/__version__.py
dbt/adapters/fabric/fabric_adapter.py
dbt/adapters/fabric/fabric_column.py
dbt/adapters/fabric/fabric_configs.py
dbt/adapters/fabric/fabric_connection_manager.py
dbt/adapters/fabric/fabric_credentials.py
dbt/adapters/fabric/fabric_relation.py
dbt/adapters/fabric/warehouse_snapshots.py
dbt/adapters/fabric/relation_configs/__init__.py
dbt/adapters/fabric/relation_configs/base.py
dbt/adapters/fabric/relation_configs/policies.py
dbt/include/fabric/__init__.py
dbt/include/fabric/dbt_project.yml
dbt/include/fabric/macros/adapters/apply_grants.sql
dbt/include/fabric/macros/adapters/catalog.sql
dbt/include/fabric/macros/adapters/columns.sql
dbt/include/fabric/macros/adapters/indexes.sql
dbt/include/fabric/macros/adapters/metadata.sql
dbt/include/fabric/macros/adapters/persist_docs.sql
dbt/include/fabric/macros/adapters/relation.sql
dbt/include/fabric/macros/adapters/schema.sql
dbt/include/fabric/macros/adapters/show.sql
dbt/include/fabric/macros/materializations/models/incremental/incremental.sql
dbt/include/fabric/macros/materializations/models/incremental/incremental_strategies.sql
dbt/include/fabric/macros/materializations/models/incremental/merge.sql
dbt/include/fabric/macros/materializations/models/table/clone.sql
dbt/include/fabric/macros/materializations/models/table/columns_spec_ddl.sql
dbt/include/fabric/macros/materializations/models/table/create_table_as.sql
dbt/include/fabric/macros/materializations/models/table/table.sql
dbt/include/fabric/macros/materializations/models/unit_test/unit_test_create_table_as.sql
dbt/include/fabric/macros/materializations/models/unit_test/unit_test_table.sql
dbt/include/fabric/macros/materializations/models/view/create_view_as.sql
dbt/include/fabric/macros/materializations/models/view/view.sql
dbt/include/fabric/macros/materializations/seeds/helpers.sql
dbt/include/fabric/macros/materializations/snapshots/helpers.sql
dbt_fabric-1.9.8.dist-info/LICENSE
dbt_fabric-1.9.8.dist-info/METADATA
dbt_fabric-1.9.8.dist-info/WHEEL
dbt_fabric-1.9.8.dist-info/top_level.txt
dbt_fabric-1.9.8.dist-info/RECORD
