Metadata-Version: 2.1
Name: dbt-fabric
Version: 1.9.8
Summary: A Microsoft Fabric Synapse Data Warehouse adapter plugin for dbt
Home-page: https://github.com/microsoft/dbt-fabric
Author: Pradeep Srikakolapu
License: MIT
Project-URL: Setup & configuration, https://docs.getdbt.com/reference/warehouse-profiles/fabric-profile
Project-URL: Documentation & usage, https://docs.getdbt.com/reference/resource-configs/fabric-configs
Project-URL: Changelog, https://github.com/microsoft/dbt-fabric/blob/master/CHANGELOG.md
Project-URL: Issue Tracker, https://github.com/microsoft/dbt-fabric/issues
Classifier: Development Status :: 5 - Production/Stable
Classifier: License :: OSI Approved :: MIT License
Classifier: Operating System :: Microsoft :: Windows
Classifier: Operating System :: MacOS :: MacOS X
Classifier: Operating System :: POSIX :: Linux
Classifier: Programming Language :: Python :: 3.8
Classifier: Programming Language :: Python :: 3.9
Classifier: Programming Language :: Python :: 3.10
Classifier: Programming Language :: Python :: 3.11
License-File: LICENSE
Requires-Dist: pyodbc>=5.2.0
Requires-Dist: azure-identity>=1.14.0
Requires-Dist: azure-core>=1.26.0
Requires-Dist: dbt-common<2.0,>=1.0.4
Requires-Dist: dbt-core>=1.8.0
Requires-Dist: dbt-adapters<2.0,>=1.1.1
